Workbook

Sheet Assumptions
A1: CSSI Elements Budget Assumptions
A2: EDIT the yellow cells only. All figures are PLACEHOLDERS — replace with real GT/Emory rates.
A4: Personnel
A5: PI (Kyanjo) 12-month base salary ($/yr) | B5: 85000 | C5: PLACEHOLDER — replace with actual GT rate
A6: PI effort committed to this award (%) | B6: 0.6
A7: Co-PI (Robel) 9-month academic-year salary ($/yr) | B7: 130000 | C7: PLACEHOLDER — replace with actual GT rate
A8: Co-PI summer months committed per year | B8: 1
A9: Annual salary escalation rate | B9: 0.03
A10: Fringe benefit rate | B10: 0.3 | C10: Confirm GT/Emory current negotiated rate
A12: Indirect Costs
A13: F&A / indirect cost rate (on MTDC) | B13: 0.57 | C13: Confirm GT's current federally negotiated rate
A15: Travel
A16: Required annual CSSI PI meeting (trips/yr) | B16: 1
A17: Cost per PI-meeting trip ($) | B17: 1800
A18: Other travel per year (conferences, fieldwork) ($) | B18: 3000
A20: Community & Workshops (Participant Support)
A21: Workshops/tutorials planned per year (#) | B21: 1
A22: Participant support cost per workshop ($) | B22: 6000 | C22: Travel/stipends for external attendees only
A24: Other Direct Costs
A25: Materials & supplies per year ($) | B25: 1500
A26: Publication / open-access costs per year ($) | B26: 1500
A27: Cloud compute costs, e.g. AWS credits per year ($) | B27: 4000 | C27: For CryoLauncher cloud-backend testing/demo
A28: RSE/student support per year ($, if any) | B28: 0 | C28: Add if funding a CI professional or grad student
A30: Program Cap
A31: CSSI Elements total budget cap ($, fixed by solicitation) | B31: 600000

Sheet Budget Summary
A1: CSSI Elements — 3-Year Budget Summary
A2: All cells here are FORMULAS driven by the Assumptions tab — edit assumptions, not these cells.
A4: Category | B4: Year 1 | C4: Year 2 | D4: Year 3 | E4: 3-Year Total
A5: Senior Personnel
A6: PI (Kyanjo) salary | B6: =Assumptions!$B$5*Assumptions!$B$6 -> 51000 | C6: =Assumptions!$B$5*Assumptions!$B$6*(1+Assumptions!$B$9) -> 52530 | D6: =Assumptions!$B$5*Assumptions!$B$6*(1+Assumptions!$B$9)^2 -> 54105.9 | E6: =SUM(B6:D6) -> 157635.9
A7: Co-PI (Robel) summer salary | B7: =(Assumptions!$B$7/9)*Assumptions!$B$8 -> 14444.444 | C7: =(Assumptions!$B$7/9)*Assumptions!$B$8*(1+Assumptions!$B$9) -> 14877.778 | D7: =(Assumptions!$B$7/9)*Assumptions!$B$8*(1+Assumptions!$B$9)^2 -> 15324.111 | E7: =SUM(B7:D7) -> 44646.333
A8: Total Senior Personnel Salary | B8: =SUM(B6:B7) -> 65444.444 | C8: =SUM(C6:C7) -> 67407.778 | D8: =SUM(D6:D7) -> 69430.011 | E8: =SUM(E6:E7) -> 202282.23
A9: Fringe Benefits | B9: =B8*Assumptions!$B$10 -> 19633.333 | C9: =C8*Assumptions!$B$10 -> 20222.333 | D9: =D8*Assumptions!$B$10 -> 20829.003 | E9: =E8*Assumptions!$B$10 -> 60684.67
A10: Total Salaries & Fringe | B10: =B8+B9 -> 85077.778 | C10: =C8+C9 -> 87630.111 | D10: =D8+D9 -> 90259.014 | E10: =E8+E9 -> 262966.9
A12: Travel
A13: PI meeting + other travel | B13: =Assumptions!$B$16*Assumptions!$B$17+Assumptions!$B$18 -> 4800 | C13: =Assumptions!$B$16*Assumptions!$B$17+Assumptions!$B$18 -> 4800 | D13: =Assumptions!$B$16*Assumptions!$B$17+Assumptions!$B$18 -> 4800 | E13: =SUM(B13:D13) -> 14400
A15: Participant Support Costs
A16: Workshops (excluded from indirect base) | B16: =Assumptions!$B$21*Assumptions!$B$22 -> 6000 | C16: =Assumptions!$B$21*Assumptions!$B$22 -> 6000 | D16: =Assumptions!$B$21*Assumptions!$B$22 -> 6000 | E16: =SUM(B16:D16) -> 18000
A18: Other Direct Costs
A19: Materials, publication, compute, RSE/student | B19: =Assumptions!$B$25+Assumptions!$B$26+Assumptions!$B$27+Assumptions!$B$28 -> 7000 | C19: =Assumptions!$B$25+Assumptions!$B$26+Assumptions!$B$27+Assumptions!$B$28 -> 7000 | D19: =Assumptions!$B$25+Assumptions!$B$26+Assumptions!$B$27+Assumptions!$B$28 -> 7000 | E19: =SUM(B19:D19) -> 21000
A21: Modified Total Direct Costs (MTDC, excl. participant support) | B21: =B10+B13+B19 -> 96877.778 | C21: =C10+C13+C19 -> 99430.111 | D21: =D10+D13+D19 -> 102059.01 | E21: =E10+E13+E19 -> 298366.9
A22: Indirect Costs (F&A) | B22: =B21*Assumptions!$B$13 -> 55220.333 | C22: =C21*Assumptions!$B$13 -> 56675.163 | D22: =D21*Assumptions!$B$13 -> 58173.638 | E22: =E21*Assumptions!$B$13 -> 170069.13
A24: TOTAL BUDGET (direct + indirect + participant support) | B24: =B21+B22+B16 -> 158098.11 | C24: =C21+C22+C16 -> 162105.27 | D24: =D21+D22+D16 -> 166232.65 | E24: =E21+E22+E16 -> 486436.04
A26: CSSI Elements cap ($600,000) — status | E26: =IF(E24<=Assumptions!$B$31,"WITHIN CAP","OVER CAP — reduce scope") -> WITHIN CAP
A27: Amount over/(under) cap | E27: =E24-Assumptions!$B$31 -> -113563.96
